pyobfuscator_gmaq/__init__.py
pyobfuscator_gmaq/cli.py
pyobfuscator_gmaq/core.py
pyobfuscator_gmaq/runtime.py
pyobfuscator_gmaq/fragments/__init__.py
pyobfuscator_gmaq/fragments/alpha.py
pyobfuscator_gmaq/fragments/beta.py
pyobfuscator_gmaq/fragments/delta.py
pyobfuscator_gmaq/fragments/epsilon.py
pyobfuscator_gmaq/fragments/gamma.py
pyobfuscator_gmaq-2.0.3.dist-info/licenses/LICENSE
pyobfuscator_gmaq-2.0.3.dist-info/METADATA
pyobfuscator_gmaq-2.0.3.dist-info/WHEEL
pyobfuscator_gmaq-2.0.3.dist-info/entry_points.txt
pyobfuscator_gmaq-2.0.3.dist-info/top_level.txt
pyobfuscator_gmaq-2.0.3.dist-info/RECORD
